Metadata-Version: 2.1
Name: mestolo
Version: 0.0.1
Summary: TODO
Author-email: "J. Marcus Hughes" <hughes.jmb@gmail.com>
Maintainer-email: "J. Marcus Hughes" <hughes.jmb@gmail.com>
Keywords: TODO
Classifier: Development Status :: 4 - Beta
Classifier: Programming Language :: Python
Requires-Python: >=3.9
Requires-Dist: click
Provides-Extra: test
Requires-Dist: pytest; extra == "test"
Requires-Dist: pytest-doctestplus; extra == "test"
Requires-Dist: pytest-cov; extra == "test"
Requires-Dist: ruff; extra == "test"
Requires-Dist: coverage; extra == "test"
Provides-Extra: docs
Requires-Dist: sphinx; extra == "docs"
Requires-Dist: sphinx-autoapi; extra == "docs"
Requires-Dist: sphinx-automodapi; extra == "docs"
Requires-Dist: pydata-sphinx-theme; extra == "docs"
Requires-Dist: sphinx-favicon; extra == "docs"
Requires-Dist: ipython; extra == "docs"
